ismi_utils/__init__.py
ismi_utils/io.py
ismi_utils-0.1.7.dist-info/LICENSE
ismi_utils-0.1.7.dist-info/METADATA
ismi_utils-0.1.7.dist-info/WHEEL
ismi_utils-0.1.7.dist-info/top_level.txt
ismi_utils-0.1.7.dist-info/RECORD
