Metadata-Version: 2.1
Name: ismi-utils
Version: 0.1.7
Summary: ISMI Utilities
Home-page: https://github.com/DIAGNijmegen/ismi_utils
Author: Bram de Wilde, Stephan Dooper, Pierpaolo Vendittelli, Joeran Bosma
Author-email: Joeran.Bosma@radboudumc.nl
License: Apache 2.0
Project-URL: Bug Tracker, https://github.com/DIAGNijmegen/ismi_utils/issues
Platform: unix
Platform: linux
Platform: osx
Platform: cygwin
Platform: win32
Classifier: Programming Language :: Python :: 3
Classifier: Programming Language :: Python :: 3 :: Only
Classifier: Programming Language :: Python :: 3.6
Classifier: Programming Language :: Python :: 3.7
Classifier: Programming Language :: Python :: 3.8
Classifier: Programming Language :: Python :: 3.9
Requires-Python: >=3.6
License-File: LICENSE
Requires-Dist: matplotlib (>=3.2.0)
Requires-Dist: numpy
Requires-Dist: scipy (>=1.7.0)
Requires-Dist: tqdm
Requires-Dist: simpleitk (>=2.1.0)
Requires-Dist: scikit-learn (>=1.0.0)
Requires-Dist: requests
Requires-Dist: ipywidgets
Requires-Dist: imgaug
Provides-Extra: testing
Requires-Dist: pytest (>=6.0) ; extra == 'testing'
Requires-Dist: pytest-cov (>=2.0) ; extra == 'testing'
Requires-Dist: mypy (>=0.910) ; extra == 'testing'
Requires-Dist: flake8 (>=3.9) ; extra == 'testing'
Requires-Dist: tox (>=3.24) ; extra == 'testing'
